serverless_aurora/__init__.py
serverless_aurora/exceptions.py
serverless_aurora/mysql_error_codes.py
serverless_aurora-0.2.3.dist-info/LICENSE
serverless_aurora-0.2.3.dist-info/METADATA
serverless_aurora-0.2.3.dist-info/WHEEL
serverless_aurora-0.2.3.dist-info/top_level.txt
serverless_aurora-0.2.3.dist-info/RECORD
